json2xml_rs/__init__.py
json2xml_rs/json2xml_rs.cpython-311-darwin.so
json2xml_rs-0.1.0.dist-info/METADATA
json2xml_rs-0.1.0.dist-info/WHEEL
json2xml_rs-0.1.0.dist-info/RECORD
