Metadata-Version: 2.4
Name: json2xml_rs
Version: 0.1.0
Classifier: Programming Language :: Rust
Classifier: Programming Language :: Python :: Implementation :: CPython
Classifier: Programming Language :: Python :: Implementation :: PyPy
Summary: Fast native JSON to XML conversion - Rust extension for json2xml
License: Apache-2.0
Requires-Python: >=3.9
